cgpy/__init__.py
cgpy/cgp.py
cgpy/operation.py
test/__init__.py
test/test_cgp.py
cgpy-0.0.6.dist-info/LICENSE
cgpy-0.0.6.dist-info/METADATA
cgpy-0.0.6.dist-info/WHEEL
cgpy-0.0.6.dist-info/top_level.txt
cgpy-0.0.6.dist-info/RECORD
