Metadata-Version: 2.1
Name: cgpy
Version: 0.0.6
Summary: A Python library for Cartesian genetic programming.
Home-page: http://cgpy.org/
Author: Viktor Wase
Author-email: viktorwase@gmail.com
Classifier: Programming Language :: Python :: 3
Classifier: License :: OSI Approved :: MIT License
Classifier: Operating System :: OS Independent
License-File: LICENSE
